<?xml version="1.0" encoding="utf-8"?>
<!DOCTYPE hibernate-mapping PUBLIC "-//Hibernate/Hibernate Mapping DTD 3.0//EN"
"http://hibernate.sourceforge.net/hibernate-mapping-3.0.dtd">
<!-- 
    Mapping file autogenerated by MyEclipse Persistence Tools
-->
<hibernate-mapping>
    <class name="com.qeweb.framework.frameworkbo.SysSchemaConfig" table="QEWEB_SCHEMA_CONFIG">
        <id name="id" type="long" column="ID">
			<generator class="native" />
		</id>
		<many-to-one name="sysSchema" class="com.qeweb.framework.frameworkbo.SysSchema" column="SCHEMA_ID" lazy="false"
		fetch="select" />
        <property name="containerId" type="string">
            <column name="CONTAINER_ID" length="20" />
        </property>
        <property name="bindBO" type="string">
            <column name="BIND_BO" length="20" />
        </property>
        <property name="bindBOP" type="string">
            <column name="BIND_BOP" length="20" />
        </property>
        <property name="sourcePage" type="string">
            <column name="SOURCE_PAGE" length="200" />
        </property>
        <property name="createUserId" column="CREATE_USER_ID" type="long" update="false"/>
		<property name="createTime" column="CREATE_TIME" length="8" type="timestamp" update="false"/>
		<property name="lastModifyUserId" column="LAST_MODIFY_USER_ID" type="long" />
		<property name="lastModifyTime" column="LAST_MODIFY_TIME" length="8" type="timestamp" />
    </class>
</hibernate-mapping>
